{
	"statusCode": 200,
	"statusMsg": null,
	"requestId": "1528711121335.rRoYJ.192.168.0.114",
	"stackTrace": null,
	"object":{
		"type": "USER_REVIEWER_COACHING_ENTITY",
		"reviewerId": "4193271ef4c65a6f",
	    "reviewedAt": 1517398078,
	    "reviewerState": {
	    	"current": "SCHEDULED",
			"prev": null,
			"timestamp": 1517398078
	    },
	    "refUserNode": {
	    	"nodeId": "form-f1",
			"type": "USER_FORM",
			"userNodeVo": null
	    },
	    "score": 0,
	    "maxScore": 1500,
	    "scheduledAt": 1517298078,
	    "scheduledFrom": 1517299078,
	    "scheduledTo": 1517308078,
	    "version": 1,
		"session": 2,
		"userId": "4193271ef4c65a6e",
		"companyId": "862238801376255550",
		"gameId": "999549387255242101",
		"reviewDocs": [
			{
				"type": 93,
				"object": "999549387255242201",
				"title": "Feedback"
			}
		],
        "reviewDuration": {
        	"hour": 2,
        	"minute": 10,
        	"second": 0
        },
        "location": {
        	"latitude": 18.552755, 
        	"longitude": 73.771882,
        },
        "learnerApprovals": {
        	"0": {
        		"approved": false,
        		"comment": "Blah",
        		"timestamp": 1517298078
        	},
        	"1": {
        		"approved": true,
        		"comment": "Blah",
        		"timestamp": 1517299078
        	}
        },
		"createdAt": 1517398078,
		"updatedAt": 1517398078
	}
}